CHANGELOG.md
LICENSE
MANIFEST.in
README.rst
TODO.rst
quickstartlog.py
setup.py
quickstartlog.egg-info/PKG-INFO
quickstartlog.egg-info/SOURCES.txt
quickstartlog.egg-info/dependency_links.txt
quickstartlog.egg-info/top_level.txt