Metadata-Version: 1.1
Name: quickstartlog
Version: 0.1.13
Summary: A simple log utility for building application quickly
Home-page: https://github.com/sunjinopensource/quickstartlog/
Author: Sun Jin
Author-email: sunjinopensource@qq.com
License: UNKNOWN
Platform: UNKNOWN
Classifier: Development Status :: 3 - Alpha
Classifier: Intended Audience :: Developers
Classifier: License :: OSI Approved :: MIT License
Classifier: Operating System :: OS Independent
Classifier: Programming Language :: Python
Classifier: Programming Language :: Python :: 3
